sqlitehandler/__init__.py
phil0_sqlitehander-0.2.0.dist-info/LICENSE
phil0_sqlitehander-0.2.0.dist-info/METADATA
phil0_sqlitehander-0.2.0.dist-info/WHEEL
phil0_sqlitehander-0.2.0.dist-info/top_level.txt
phil0_sqlitehander-0.2.0.dist-info/RECORD
